SPRINT_imputations.py
__init__.py
SPRINT_imputations-1.0.3.dist-info/LICENSE
SPRINT_imputations-1.0.3.dist-info/METADATA
SPRINT_imputations-1.0.3.dist-info/WHEEL
SPRINT_imputations-1.0.3.dist-info/top_level.txt
SPRINT_imputations-1.0.3.dist-info/RECORD
