Metadata-Version: 2.1
Name: SPRINT_imputations
Version: 1.0.3
Summary: SPRINT alogrithm - For missing traffic data imputation
Author-email: Shubham Sharma <s50.sharma@qut.edu.au>
Classifier: Programming Language :: Python :: 3
Classifier: License :: OSI Approved :: MIT License
Classifier: Operating System :: OS Independent
Requires-Python: >=3.8
License-File: LICENSE
Requires-Dist: numpy
Requires-Dist: pandas
Requires-Dist: scipy
Requires-Dist: termcolor
